README.md
setup.cfg
setup.py
rca/__init__.py
rca/adapters.py
rca/exceptions.py
rca/url_parser.py
rca/scripts/__init__.py
rca/scripts/cli.py
requests_celery_adapters.egg-info/PKG-INFO
requests_celery_adapters.egg-info/SOURCES.txt
requests_celery_adapters.egg-info/dependency_links.txt
requests_celery_adapters.egg-info/entry_points.txt
requests_celery_adapters.egg-info/not-zip-safe
requests_celery_adapters.egg-info/requires.txt
requests_celery_adapters.egg-info/top_level.txt
tests/__init__.py
tests/test_calls.py
tests/test_task_parser.py