Metadata-Version: 2.1
Name: requests-celery-adapters
Version: 2.0.14
Summary: Requests lib adapters to send Celery messages (tasks)
Home-page: UNKNOWN
Author: Tomas Correa
Author-email: tomas@geru.com.br
License: UNKNOWN
Keywords: worker celery
Platform: UNKNOWN
Classifier: Programming Language :: Python
Provides-Extra: test
Provides-Extra: cli
